stms/__init__.py
stms/stms.py
stms-0.4.0.dist-info/licenses/LICENSE
stms-0.4.0.dist-info/METADATA
stms-0.4.0.dist-info/WHEEL
stms-0.4.0.dist-info/top_level.txt
stms-0.4.0.dist-info/RECORD
