Metadata-Version: 2.4
Name: stms
Version: 0.4.0
Summary: Spatiotemporal Filling and Multistep Smoothing for satellite time series reconstruction
Home-page: https://github.com/byususen/stms
Author: Bayu Suseno
Author-email: bayu.suseno@outlook.com
Classifier: Programming Language :: Python :: 3
Classifier: License :: OSI Approved :: MIT License
Classifier: Operating System :: OS Independent
Requires-Python: >=3.7
License-File: LICENSE
Requires-Dist: numpy
Requires-Dist: pygam
Requires-Dist: tqdm
Requires-Dist: matplotlib
Requires-Dist: numba
Dynamic: author
Dynamic: author-email
Dynamic: classifier
Dynamic: description
Dynamic: description-content-type
Dynamic: home-page
Dynamic: license-file
Dynamic: requires-dist
Dynamic: requires-python
Dynamic: summary
